{
  "variantName": "hero-overlay",
  "baseBlock": "hero",
  "version": "1.0.0",
  "created": "2026-07-02T00:00:00.000Z",
  "sourceContext": {
    "originUrl": "https://wknd-trendsetters.site/",
    "originPage": "WKND Trendsetters homepage",
    "blockPosition": "bottom"
  },
  "visualCharacteristics": {
    "colorScheme": "dark",
    "density": "spacious",
    "purpose": "cta-banner",
    "imagePattern": "large"
  },
  "contentPattern": {
    "structure": "background image + overlay + heading + subheading + 1 CTA",
    "buttonCount": 1,
    "imageCount": 1
  },
  "reuseGuidance": {
    "suitableFor": [
      "full-bleed CTA banners with a background image and dark overlay",
      "closing call-to-action sections with overlaid text"
    ],
    "notSuitableFor": [
      "light-background intro heroes with side image groups"
    ]
  },
  "usage": {
    "pagesUsing": ["/index"],
    "reuseCount": 1,
    "lastUsed": "2026-07-02T00:00:00.000Z"
  }
}
